stone/__init__.py
stone/__main__.py
stone/api.py
stone/image.py
stone/package.py
stone/utils.py
stone/ui/__init__.py
stone/ui/config_icon.png
stone/ui/program_icon.png
skin_tone_classifier-1.2.5.dist-info/LICENSE
skin_tone_classifier-1.2.5.dist-info/METADATA
skin_tone_classifier-1.2.5.dist-info/WHEEL
skin_tone_classifier-1.2.5.dist-info/entry_points.txt
skin_tone_classifier-1.2.5.dist-info/top_level.txt
skin_tone_classifier-1.2.5.dist-info/RECORD
