Metadata-Version: 2.2
Name: skin-tone-classifier
Version: 1.2.5
Summary: An easy-to-use library for skin tone classification
Author-email: Chenglong Ma <chenglong.m@outlook.com>
Maintainer-email: Chenglong Ma <chenglong.m@outlook.com>
Project-URL: Homepage, https://chenglongma.com/SkinToneClassifier/
Project-URL: Bug Reports, https://github.com/ChenglongMa/SkinToneClassifier/issues
Project-URL: Funding, https://github.com/sponsors/ChenglongMa
Project-URL: Say Thanks!, https://saythanks.io/to/ChenglongMa
Project-URL: Repository, https://github.com/ChenglongMa/SkinToneClassifier/
Project-URL: Changelog, https://github.com/ChenglongMa/SkinToneClassifier/blob/main/CHANGELOG.md
Keywords: skin tone,image recognition,face detection,skin detection,image segmentation
Classifier: Development Status :: 5 - Production/Stable
Classifier: Intended Audience :: End Users/Desktop
Classifier: Intended Audience :: Information Technology
Classifier: Intended Audience :: Science/Research
Classifier: Programming Language :: Python :: 3.9
Classifier: Programming Language :: Python :: 3.10
Classifier: Programming Language :: Python :: 3.11
Classifier: Programming Language :: Python :: 3.12
Classifier: Programming Language :: Python :: 3.13
Classifier: License :: OSI Approved :: GNU General Public License v3 (GPLv3)
Classifier: Operating System :: OS Independent
Classifier: Topic :: Scientific/Engineering :: Image Recognition
Classifier: Topic :: Scientific/Engineering :: Image Processing
Classifier: Topic :: Scientific/Engineering :: Artificial Intelligence
Classifier: Topic :: Scientific/Engineering :: Information Analysis
Classifier: Topic :: Scientific/Engineering :: Visualization
Classifier: Topic :: Sociology
Classifier: Topic :: Multimedia :: Graphics
Classifier: Topic :: Software Development :: Libraries :: Python Modules
Classifier: Topic :: Terminals
Classifier: Environment :: Console
Classifier: Environment :: Web Environment
Classifier: Environment :: Win32 (MS Windows)
Classifier: Environment :: MacOS X
Classifier: Environment :: Other Environment
Requires-Python: >=3.9
License-File: LICENSE
Requires-Dist: opencv-python>=4.9.0.80
Requires-Dist: numpy>=1.21.5
Requires-Dist: colormath>=3.0.0
Requires-Dist: tqdm>=4.64.0
Requires-Dist: colorama>=0.4.6
Requires-Dist: packaging>=23.1
Requires-Dist: requests>=2.31.0
Provides-Extra: all
Requires-Dist: gooey>=1.0.8.1; extra == "all"
Requires-Dist: re-wx==0.0.10; extra == "all"
Requires-Dist: colored==1.4.4; extra == "all"
